HibernateGaojiJiaocheng/README.md
HibernateGaojiJiaocheng/__init__.py
HibernateGaojiJiaocheng/__main__.py
HibernateGaojiJiaocheng/file.epub
HibernateGaojiJiaocheng/index.html
HibernateGaojiJiaocheng/css/__init__.py
HibernateGaojiJiaocheng/css/annotations.css
HibernateGaojiJiaocheng/css/main.css
HibernateGaojiJiaocheng/css/normalize.css
HibernateGaojiJiaocheng/css/popup.css
HibernateGaojiJiaocheng/font/__init__.py
HibernateGaojiJiaocheng/font/fontello.eot
HibernateGaojiJiaocheng/font/fontello.svg
HibernateGaojiJiaocheng/font/fontello.ttf
HibernateGaojiJiaocheng/font/fontello.woff
HibernateGaojiJiaocheng/img/__init__.py
HibernateGaojiJiaocheng/img/annotator-glyph-sprite.png
HibernateGaojiJiaocheng/img/annotator-icon-sprite.png
HibernateGaojiJiaocheng/img/apple-touch-icon.png
HibernateGaojiJiaocheng/img/cancelfullscreen.png
HibernateGaojiJiaocheng/img/close.png
HibernateGaojiJiaocheng/img/fullscreen.png
HibernateGaojiJiaocheng/img/loader.gif
HibernateGaojiJiaocheng/img/menu-icon.png
HibernateGaojiJiaocheng/img/save.png
HibernateGaojiJiaocheng/img/saved.png
HibernateGaojiJiaocheng/img/settings-s.png
HibernateGaojiJiaocheng/img/settings.png
HibernateGaojiJiaocheng/img/star.png
HibernateGaojiJiaocheng/js/__init__.py
HibernateGaojiJiaocheng/js/epub.js
HibernateGaojiJiaocheng/js/epub.min.js
HibernateGaojiJiaocheng/js/epub.min.map
HibernateGaojiJiaocheng/js/hooks.min.js
HibernateGaojiJiaocheng/js/hooks.min.map
HibernateGaojiJiaocheng/js/reader.js
HibernateGaojiJiaocheng/js/reader.js.map
HibernateGaojiJiaocheng/js/reader.min.js
HibernateGaojiJiaocheng/js/reader.min.map
HibernateGaojiJiaocheng/js/hooks/__init__.py
HibernateGaojiJiaocheng/js/hooks/extensions/__init__.py
HibernateGaojiJiaocheng/js/hooks/extensions/highlight.js
HibernateGaojiJiaocheng/js/libs/__init__.py
HibernateGaojiJiaocheng/js/libs/jquery.min.js
HibernateGaojiJiaocheng/js/libs/localforage.min.js
HibernateGaojiJiaocheng/js/libs/screenfull.js
HibernateGaojiJiaocheng/js/libs/screenfull.min.js
hibernate_gaoji_jiaocheng-2024.3.4.0.dist-info/METADATA
hibernate_gaoji_jiaocheng-2024.3.4.0.dist-info/WHEEL
hibernate_gaoji_jiaocheng-2024.3.4.0.dist-info/entry_points.txt
hibernate_gaoji_jiaocheng-2024.3.4.0.dist-info/top_level.txt
hibernate_gaoji_jiaocheng-2024.3.4.0.dist-info/RECORD
